lambdacore/__init__.py
lambdacore/cloud.py
lambdacore/environment.py
lambdacore/example_function.py
lambdacore/generic_function.py
lambdacore/logger.py
lambdacore/run.py
lambdacore-0.1.dist-info/DESCRIPTION.rst
lambdacore-0.1.dist-info/METADATA
lambdacore-0.1.dist-info/RECORD
lambdacore-0.1.dist-info/WHEEL
lambdacore-0.1.dist-info/metadata.json
lambdacore-0.1.dist-info/top_level.txt
