Metadata-Version: 2.0
Name: lambdacore
Version: 0.1
Summary: Object-oriented framework for building Lambda functions in AWS
Home-page: https://github.com/jacobneiltaylor/lambdacore
Author: Jacob Neil Taylor
Author-email: me@jacobtaylor.id.au
License: LGPLv3
Platform: UNKNOWN
Classifier: Development Status :: 2 - Pre-Alpha
Classifier: Environment :: Other Environment
Classifier: Intended Audience :: Developers
Classifier: Topic :: Software Development :: Libraries
Classifier: License :: OSI Approved :: GNU Lesser General Public License v3 (LGPLv3)
